pytidb/__init__.py
pytidb/base.py
pytidb/client.py
pytidb/databases.py
pytidb/datatype.py
pytidb/errors.py
pytidb/filters.py
pytidb/fusion.py
pytidb/logger.py
pytidb/py.typed
pytidb/result.py
pytidb/schema.py
pytidb/search.py
pytidb/sql.py
pytidb/table.py
pytidb/utils.py
pytidb/embeddings/__init__.py
pytidb/embeddings/aliases.py
pytidb/embeddings/base.py
pytidb/embeddings/builtin.py
pytidb/embeddings/dimensions.py
pytidb/embeddings/utils.py
pytidb/ext/__init__.py
pytidb/ext/mcp/__init__.py
pytidb/ext/mcp/__main__.py
pytidb/ext/mcp/server.py
pytidb/orm/__init__.py
pytidb/orm/_typing.py
pytidb/orm/distance_metric.py
pytidb/orm/functions.py
pytidb/orm/indexes.py
pytidb/orm/information_schema.py
pytidb/orm/tiflash_replica.py
pytidb/orm/types.py
pytidb/orm/variables.py
pytidb/orm/vector.py
pytidb/orm/sql/ddl.py
pytidb/rerankers/__init__.py
pytidb/rerankers/base.py
pytidb/rerankers/litellm.py
pytidb-0.0.13.dist-info/METADATA
pytidb-0.0.13.dist-info/WHEEL
pytidb-0.0.13.dist-info/entry_points.txt
pytidb-0.0.13.dist-info/licenses/LICENSE
pytidb-0.0.13.dist-info/RECORD
