Metadata-Version: 2.3
Name: pytidb
Version: 0.0.13
Summary: A Python library for TiDB.
Author-email: Mini256 <minianter@foxmail.com>, sykp241095 <sykp241095@gmail.com>
Requires-Python: >=3.10
Requires-Dist: numpy<3,>=1
Requires-Dist: pymysql>=1.1.1
Requires-Dist: sqlalchemy<3,>=1.4
Requires-Dist: sqlmodel>=0.0.14
Provides-Extra: mcp
Requires-Dist: mcp; extra == 'mcp'
Requires-Dist: mcp[cli]>=1.6.0; extra == 'mcp'
Provides-Extra: models
Requires-Dist: litellm<2.0.0,>=1.59.8; extra == 'models'
Requires-Dist: pillow; extra == 'models'
Provides-Extra: pandas
Requires-Dist: pandas; extra == 'pandas'
